fastcs/__init__.py
fastcs/_version.py
fastcs/attributes.py
fastcs/backend.py
fastcs/controller.py
fastcs/controller_api.py
fastcs/cs_methods.py
fastcs/datatypes.py
fastcs/exceptions.py
fastcs/launch.py
fastcs/util.py
fastcs/wrappers.py
fastcs/connections/__init__.py
fastcs/connections/ip_connection.py
fastcs/connections/serial_connection.py
fastcs/demo/__init__.py
fastcs/demo/__main__.py
fastcs/demo/controller.yaml
fastcs/demo/controllers.py
fastcs/demo/schema.json
fastcs/demo/simulation/__init__.py
fastcs/demo/simulation/device.py
fastcs/demo/simulation/temp_controller.yaml
fastcs/transport/__init__.py
fastcs/transport/adapter.py
fastcs/transport/epics/__init__.py
fastcs/transport/epics/docs.py
fastcs/transport/epics/gui.py
fastcs/transport/epics/options.py
fastcs/transport/epics/ca/__init__.py
fastcs/transport/epics/ca/adapter.py
fastcs/transport/epics/ca/ioc.py
fastcs/transport/epics/ca/options.py
fastcs/transport/epics/ca/util.py
fastcs/transport/epics/pva/__init__.py
fastcs/transport/epics/pva/_pv_handlers.py
fastcs/transport/epics/pva/adapter.py
fastcs/transport/epics/pva/ioc.py
fastcs/transport/epics/pva/options.py
fastcs/transport/epics/pva/pvi_tree.py
fastcs/transport/epics/pva/types.py
fastcs/transport/graphQL/__init__.py
fastcs/transport/graphQL/adapter.py
fastcs/transport/graphQL/graphQL.py
fastcs/transport/graphQL/options.py
fastcs/transport/rest/__init__.py
fastcs/transport/rest/adapter.py
fastcs/transport/rest/options.py
fastcs/transport/rest/rest.py
fastcs/transport/rest/util.py
fastcs/transport/tango/__init__.py
fastcs/transport/tango/adapter.py
fastcs/transport/tango/dsr.py
fastcs/transport/tango/options.py
fastcs/transport/tango/util.py
fastcs-2025.8.1.dist-info/licenses/LICENSE
fastcs-2025.8.1.dist-info/METADATA
fastcs-2025.8.1.dist-info/WHEEL
fastcs-2025.8.1.dist-info/entry_points.txt
fastcs-2025.8.1.dist-info/top_level.txt
fastcs-2025.8.1.dist-info/RECORD
