Metadata-Version: 2.4
Name: fastcs
Version: 2025.8.1
Summary: Control system agnostic framework for building Device support in Python that will work for both EPICS and Tango
Author-email: Martin Gaughran <martin.gaughran@diamond.ac.uk>
License:                                  Apache License
Project-URL: GitHub, https://github.com/DiamondLightSource/FastCS
Classifier: Development Status :: 3 - Alpha
Classifier: License :: OSI Approved :: Apache Software License
Classifier: Programming Language :: Python :: 3.11
Classifier: Programming Language :: Python :: 3.12
Requires-Python: >=3.11
License-File: LICENSE
Requires-Dist: aioserial
Requires-Dist: fastapi[standard]
Requires-Dist: numpy
Requires-Dist: pydantic
Requires-Dist: pvi~=0.10.0
Requires-Dist: pytango
Requires-Dist: softioc>=4.5.0
Requires-Dist: strawberry-graphql
Requires-Dist: p4p
Provides-Extra: dev
Requires-Dist: copier; extra == "dev"
Requires-Dist: myst-parser; extra == "dev"
Requires-Dist: pipdeptree; extra == "dev"
Requires-Dist: pre-commit; extra == "dev"
Requires-Dist: pydata-sphinx-theme>=0.12; extra == "dev"
Requires-Dist: pyright; extra == "dev"
Requires-Dist: pytest; extra == "dev"
Requires-Dist: pytest-benchmark; extra == "dev"
Requires-Dist: pytest-cov; extra == "dev"
Requires-Dist: pytest-mock; extra == "dev"
Requires-Dist: pytest-asyncio; extra == "dev"
Requires-Dist: pytest-markdown-docs; extra == "dev"
Requires-Dist: ruff; extra == "dev"
Requires-Dist: sphinx-autobuild; extra == "dev"
Requires-Dist: sphinx-copybutton; extra == "dev"
Requires-Dist: sphinx-togglebutton; extra == "dev"
Requires-Dist: sphinx-design; extra == "dev"
Requires-Dist: tox-direct; extra == "dev"
Requires-Dist: types-mock; extra == "dev"
Requires-Dist: aioca; extra == "dev"
Requires-Dist: p4p; extra == "dev"
Requires-Dist: httpx; extra == "dev"
Requires-Dist: tickit~=0.4.3; extra == "dev"
Provides-Extra: demo
Requires-Dist: tickit~=0.4.3; extra == "demo"
Dynamic: license-file
